cloudstorageimageresizer
