Metadata-Version: 2.1
Name: google-cloud-storage-image-resizer
Version: 2.36.0
Summary: Import, rotate, crop and resize pictures into google Cloud Storage
Home-page: https://github.com/erwan-lemonnier/cloud-storage-image-resizer
Author: Erwan Lemonnier
Author-email: erwan@lemonnier.se
License: BSD
Platform: any
Classifier: Environment :: Web Environment
Classifier: Intended Audience :: Developers
Classifier: License :: OSI Approved :: BSD License
Classifier: Operating System :: OS Independent
Classifier: Programming Language :: Python
Classifier: Topic :: Internet :: WWW/HTTP :: Dynamic Content
Classifier: Topic :: Software Development :: Libraries :: Python Modules
